ADattribution/__init__.py
ADattribution/adq_postback.py
ADattribution/baidu_postback.py
ADattribution/oceanengine_postback.py
ADattribution-0.0.10.dist-info/LICENSE
ADattribution-0.0.10.dist-info/METADATA
ADattribution-0.0.10.dist-info/WHEEL
ADattribution-0.0.10.dist-info/top_level.txt
ADattribution-0.0.10.dist-info/RECORD
