Metadata-Version: 2.1
Name: ADattribution
Version: 0.0.10
Summary: make it easy to use AD postback
Home-page: https://gitee.com/ZeroSeeker/ADattribution
Author: ZeroSeeker
Author-email: zeroseeker@foxmail.com
Classifier: Programming Language :: Python :: 3
Classifier: Operating System :: OS Independent
License-File: LICENSE
Requires-Dist: ua-parser (==0.10.0)
Requires-Dist: lazysdk (>=0.1.91)
